simforge/__init__.py
simforge/__main__.py
simforge/py.typed
simforge/_typing/__init__.py
simforge/_typing/cfg.py
simforge/_typing/enum.py
simforge/core/__init__.py
simforge/core/asset/__init__.py
simforge/core/asset/articulation.py
simforge/core/asset/asset.py
simforge/core/asset/asset_type.py
simforge/core/asset/geometry.py
simforge/core/asset/image.py
simforge/core/asset/material.py
simforge/core/asset/model.py
simforge/core/baker/__init__.py
simforge/core/baker/bake_type.py
simforge/core/baker/baker.py
simforge/core/exporter/__init__.py
simforge/core/exporter/exporter.py
simforge/core/exporter/file_format.py
simforge/core/generator/__init__.py
simforge/core/generator/generator.py
simforge/core/procgen/__init__.py
simforge/core/procgen/op_type.py
simforge/core/procgen/proc_op.py
simforge/core/renderer/__init__.py
simforge/core/renderer/renderer.py
simforge/core/semantics/__init__.py
simforge/core/semantics/semantic_class.py
simforge/core/semantics/semantic_tag.py
simforge/core/semantics/semantics.py
simforge/generators/__init__.py
simforge/generators/blender/__init__.py
simforge/generators/blender/baker.py
simforge/generators/blender/exporter.py
simforge/generators/blender/generator.py
simforge/generators/blender/importer.py
simforge/generators/blender/version.py
simforge/generators/blender/asset/__init__.py
simforge/generators/blender/asset/articulation.py
simforge/generators/blender/asset/geometry.py
simforge/generators/blender/asset/image.py
simforge/generators/blender/asset/material.py
simforge/generators/blender/asset/model.py
simforge/generators/blender/modifier/__init__.py
simforge/generators/blender/modifier/decimate.py
simforge/generators/blender/modifier/geometry_nodes.py
simforge/generators/blender/modifier/modifier.py
simforge/generators/blender/modifier/triangulate.py
simforge/generators/blender/nodes/__init__.py
simforge/generators/blender/nodes/nodes.py
simforge/generators/blender/nodes/nodes_from_python.py
simforge-0.2.4.dist-info/METADATA
simforge-0.2.4.dist-info/WHEEL
simforge-0.2.4.dist-info/entry_points.txt
simforge-0.2.4.dist-info/licenses/LICENSE-APACHE
simforge-0.2.4.dist-info/licenses/LICENSE-MIT
simforge-0.2.4.dist-info/RECORD
