Metadata-Version: 2.4
Name: simforge
Version: 0.2.4
Summary: Diverse virtual environments through procedural generation
Project-URL: Repository, https://github.com/AndrejOrsula/simforge
Project-URL: Documentation, https://AndrejOrsula.github.io/simforge
Author-email: Andrej Orsula <orsula.andrej@gmail.com>
Maintainer-email: Andrej Orsula <orsula.andrej@gmail.com>
License: MIT OR Apache-2.0
License-File: LICENSE-APACHE
License-File: LICENSE-MIT
Keywords: procedural,simulation
Classifier: License :: OSI Approved :: Apache Software License
Classifier: License :: OSI Approved :: MIT License
Classifier: Programming Language :: Python
Classifier: Topic :: Games/Entertainment :: Simulation
Classifier: Topic :: Multimedia :: Graphics :: 3D Modeling
Requires-Python: >=3.11
Requires-Dist: platformdirs~=4.0
Requires-Dist: pydantic~=2.0
Requires-Dist: pytest-cov>=7.0.0
Provides-Extra: all
Requires-Dist: argcomplete~=3.0; extra == 'all'
Requires-Dist: bpy~=4.0; extra == 'all'
Requires-Dist: fake-bpy-module; extra == 'all'
Requires-Dist: logfire~=4.0; extra == 'all'
Requires-Dist: ptpython~=3.0; extra == 'all'
Requires-Dist: pytest-order~=1.0; extra == 'all'
Requires-Dist: pytest-sugar~=1.0; extra == 'all'
Requires-Dist: pytest~=8.0; extra == 'all'
Requires-Dist: rich~=14.0; extra == 'all'
Requires-Dist: simforge-foundry; extra == 'all'
Provides-Extra: assets
Requires-Dist: simforge-foundry; extra == 'assets'
Provides-Extra: bpy
Requires-Dist: bpy~=4.0; extra == 'bpy'
Provides-Extra: bpydev
Requires-Dist: bpy~=4.0; extra == 'bpydev'
Requires-Dist: fake-bpy-module; extra == 'bpydev'
Provides-Extra: cli
Requires-Dist: argcomplete~=3.0; extra == 'cli'
Requires-Dist: ptpython~=3.0; extra == 'cli'
Requires-Dist: rich~=14.0; extra == 'cli'
Provides-Extra: dev
Requires-Dist: logfire~=4.0; extra == 'dev'
Requires-Dist: pytest-order~=1.0; extra == 'dev'
Requires-Dist: pytest-sugar~=1.0; extra == 'dev'
Requires-Dist: pytest~=8.0; extra == 'dev'
Requires-Dist: rich~=14.0; extra == 'dev'
Provides-Extra: foundry
Requires-Dist: simforge-foundry; extra == 'foundry'
Provides-Extra: repl
Requires-Dist: ptpython~=3.0; extra == 'repl'
Provides-Extra: rich
Requires-Dist: rich~=14.0; extra == 'rich'
Provides-Extra: test
Requires-Dist: pytest-order~=1.0; extra == 'test'
Requires-Dist: pytest-sugar~=1.0; extra == 'test'
Requires-Dist: pytest~=8.0; extra == 'test'
Provides-Extra: tracing
Requires-Dist: logfire~=4.0; extra == 'tracing'
Requires-Dist: rich~=14.0; extra == 'tracing'
